{
	"backtraceGraph" : 
	{
		"commands" : 
		[
			"install"
		],
		"files" : 
		[
			"src/stella_vslam/initialize/CMakeLists.txt"
		],
		"nodes" : 
		[
			{
				"file" : 0
			},
			{
				"command" : 0,
				"file" : 0,
				"line" : 13,
				"parent" : 0
			}
		]
	},
	"installers" : 
	[
		{
			"backtrace" : 1,
			"component" : "Unspecified",
			"destination" : "include/stella_vslam/initialize",
			"paths" : 
			[
				"src/stella_vslam/initialize/base.h",
				"src/stella_vslam/initialize/bearing_vector.h",
				"src/stella_vslam/initialize/perspective.h"
			],
			"type" : "file"
		}
	],
	"paths" : 
	{
		"build" : "src/stella_vslam/initialize",
		"source" : "src/stella_vslam/initialize"
	}
}
